llama_index/readers/llama_parse/BUILD
llama_index/readers/llama_parse/__init__.py
llama_index_readers_llama_parse-0.1.2.dist-info/METADATA
llama_index_readers_llama_parse-0.1.2.dist-info/WHEEL
llama_index_readers_llama_parse-0.1.2.dist-info/RECORD
