Metadata-Version: 2.1
Name: llama-index-readers-llama-parse
Version: 0.1.2
Summary: llama-index readers llama-parse integration
License: MIT
Keywords: PDF,llama,llama-parse,parse
Author: Logan Markewich
Author-email: logan@runllama.ai
Requires-Python: >=3.8.1,<4.0
Classifier: License :: OSI Approved :: MIT License
Classifier: Programming Language :: Python :: 3
Classifier: Programming Language :: Python :: 3.9
Classifier: Programming Language :: Python :: 3.10
Classifier: Programming Language :: Python :: 3.11
Classifier: Programming Language :: Python :: 3.12
Requires-Dist: llama-index-core (>=0.10.7,<0.11.0)
Requires-Dist: llama-parse (>=0.3.3,<0.4.0)
